<?xml version="1.0" encoding="utf-8"?>
<resources>
    <a>Привет сталкер!</a>
    <a tag="b">Как дела что нового?</a>
    <a type="3">Торговать.</a>
    <a tag="c" type="2" qvest="0">Слышал у тебя для меня задание есть.</a>
    <a tag="i">Кошмар, цены у тебя кошмарные!</a>
    <a type="4">Пока.</a>
    <b>Представляеш вчера с другом ходили на кабанов, ушли мы далековато и не заметели как стемнело, уже собрались обратно идти, как вдруг наткнулись на толпу зомби. Стрелять было нечем, все патроны на кабанов ушли поэтому мы дали деру. Бегу я значит, а стемнело уже ничего невидать, ну и я прям в аномалию капкан и вступил. Она вокруг меня обвилась, не шевельнуться. Хорошо, друг мой "Вымпел" заметил что я в беде, подскочил и ножем разрезал ткань аномалии. Эх если бы не он сожрали бы меня зомби, так что в зоне без друзей или товарищей долго не протянеш.</b>
    <b tag="a">Да уж вот так исторя!</b>
    <c>Не мог бы ты зарядить мне аккумулятор. Дело не пыльное, надо найти любую передвигающуюся аномалию искра и кинуть под неё аккумулятор, так он мигом зарядится. Я видал такую аномалию в квадрате 9 прям на железной дороге была. Как зарядиш неси ко мне, я тебе за это ствол старенький подгоню. Этот квест можно выполнить только 1 раз.</c>
    <c type="1" send="1/12/1" addqvest="true">Да не вопрос, давай аккумулятор.</c>
    <c tag="a">Не, боюсь я этих аномалий.</c>
    <c1>Притащил ?</c1>
    <c1 tag="d" type="1" send="1/12/2">Конечно!</c1>
    <c1 tag="a">Пока нет.</c1>
    <d>Cпасибо выручил, держи ствол.</d>
    <d tag="a">Спасибо.</d>
    <d1>Друг, так он ведь незаряжен.</d1>
    <d1 tag="a">Действительно, что то я затупил.</d1>
    <i>Не смешно, ты сегодня двадцать третий кто мне об этом говорит.</i>
    <i tag="a">Понял.</i>
</resources>